mindwavelsl/__init__.py
mindwavelsl/connectors.py
mindwavelsl/constants.py
mindwavelsl/logger.py
mindwavelsl/mindwavelsl.py
mindwavelsl/outlet.py
mindwavelsl/parser.py
mindwavelsl/vendor/mindwave.py
mindwavelsl-1.1.0.dist-info/METADATA
mindwavelsl-1.1.0.dist-info/WHEEL
mindwavelsl-1.1.0.dist-info/entry_points.txt
mindwavelsl-1.1.0.dist-info/top_level.txt
mindwavelsl-1.1.0.dist-info/RECORD
